chapters/Chapter1.py
chapters/Chapter10.py
chapters/Chapter11.py
chapters/Chapter12.py
chapters/Chapter13.py
chapters/Chapter14.py
chapters/Chapter15.py
chapters/Chapter16.py
chapters/Chapter17.py
chapters/Chapter18.py
chapters/Chapter19.py
chapters/Chapter2.py
chapters/Chapter20.py
chapters/Chapter3.py
chapters/Chapter4.py
chapters/Chapter5.py
chapters/Chapter6.py
chapters/Chapter7.py
chapters/Chapter8.py
chapters/Chapter9.py
fgn/__init__.py
fgn/cli.py
fgn/skeleton.py
fgn/__pycache__/__init__.py
fgn/completion/__init__.py
fgn/completion/chat.py
fgn/completion/complete.py
fgn/completion/history.py
fgn/completion/output.txt
fgn/completion/output0.py
fgn/completion/output2.txt
fgn/completion/output3.txt
fgn/completion/prompt_schemas.py
fgn/completion/__pycache__/__init__.py
fgn/core/__init__.py
fgn/core/chat_agent.py
fgn/core/command_context.py
fgn/core/core_cmd.py
fgn/core/default_sub_cmd.py
fgn/core/dsl_parser.py
fgn/core/fgn_cli.py
fgn/core/__pycache__/__init__.py
fgn/core/commands/__init__.py
fgn/core/commands/blog/__init__.py
fgn/core/commands/blog/blog_cmd.py
fgn/core/commands/blog/blog_config.yml
fgn/core/commands/blog/blog_example.txt
fgn/core/commands/blog/blog_history.txt
fgn/core/commands/blog/blog_system_prompt.txt
fgn/core/commands/blog/blog_template.txt
fgn/core/commands/blog/__pycache__/__init__.py
fgn/core/commands/chain/__init__.py
fgn/core/commands/chain/chain_cmd.py
fgn/core/commands/chain/chain_config.yml
fgn/core/commands/chain/chain_example.txt
fgn/core/commands/chain/chain_history.txt
fgn/core/commands/chain/chain_system_prompt.txt
fgn/core/commands/chain/chain_template.txt
fgn/core/commands/chain/__pycache__/__init__.py
fgn/core/commands/code/__init__.py
fgn/core/commands/code/code_cmd.py
fgn/core/commands/code/code_config.yml
fgn/core/commands/code/code_example.txt
fgn/core/commands/code/code_history.txt
fgn/core/commands/code/code_schema.txt
fgn/core/commands/code/code_system_prompt.txt
fgn/core/commands/code/code_template.txt
fgn-2023.9.29.dist-info/LICENSE.txt
fgn-2023.9.29.dist-info/METADATA
fgn-2023.9.29.dist-info/WHEEL
fgn-2023.9.29.dist-info/__init__.py
fgn-2023.9.29.dist-info/entry_points.txt
fgn-2023.9.29.dist-info/top_level.txt
fgn-2023.9.29.dist-info/RECORD
