Metadata-Version: 2.1
Name: fgn
Version: 2023.9.29
Summary: FGN: An AI-powered command-line tool for automated file generation.
Home-page: https://github.com/seanchatmangpt/fgn
Author: Sean Chatman
Author-email: info@chatmangpt.com
License: MIT
Project-URL: Documentation, https://pyscaffold.org/
Platform: any
Classifier: Development Status :: 4 - Beta
Classifier: Programming Language :: Python
License-File: LICENSE.txt
Requires-Dist: click
Requires-Dist: pyfakefs
Requires-Dist: rich
Requires-Dist: openai
Requires-Dist: PyGithub
Requires-Dist: pytest
Requires-Dist: PyYAML
Requires-Dist: distro
Requires-Dist: markdown2
Requires-Dist: lxml
Requires-Dist: requests
Requires-Dist: pytest-mock
Requires-Dist: pyyaml
Requires-Dist: jinja2 (>=3.1.0)
Requires-Dist: inflection (>=0.5.1)
Requires-Dist: faker (>=19.2.0)
Requires-Dist: jinja2-time
Requires-Dist: dataclasses-json
Requires-Dist: loguru
Requires-Dist: importlib-metadata ; python_version < "3.11"
Provides-Extra: testing
Requires-Dist: setuptools ; extra == 'testing'
Requires-Dist: pytest ; extra == 'testing'
Requires-Dist: pytest-cov ; extra == 'testing'
